{
 "TCS": "NSE_EQ|INE467B01029",
 "HINDUNILVR": "NSE_EQ|INE030A01027",
 "SUNPHARMA": "NSE_EQ|INE044A01036",
 "INFY": "NSE_EQ|INE009A01021",
 "ULTRACEMCO": "NSE_EQ|INE481G01011",
 "HCLTECH": "NSE_EQ|INE860A01027",
 "ONGC": "NSE_EQ|INE213A01029",
 "DMART": "NSE_EQ|INE192R01011",
 "ASIANPAINT": "NSE_EQ|INE021A01026",
 "HINDALCO": "NSE_EQ|INE038A01020",
 "TORNTPHARM": "NSE_EQ|INE685A01028",
 "PIDILITIND": "NSE_EQ|INE318A01026",
 "HYUNDAI": "NSE_EQ|INE0V6F01027",
 "CUMMINSIND": "NSE_EQ|INE298A01020",
 "TRENT": "NSE_EQ|INE849A01020",
 "MOTHERSON": "NSE_EQ|INE775A01035",
 "CGPOWER": "NSE_EQ|INE067A01029",
 "TECHM": "NSE_EQ|INE669C01036",
 "POLYCAB": "NSE_EQ|INE455K01017",
 "BHEL": "NSE_EQ|INE257A01026",
 "BPCL": "NSE_EQ|INE029A01011",
 "BRITANNIA": "NSE_EQ|INE216A01030",
 "LODHA": "NSE_EQ|INE670K01029",
 "CIPLA": "NSE_EQ|INE059A01026",
 "ZYDUSLIFE": "NSE_EQ|INE010B01027",
 "GAIL": "NSE_EQ|INE129A01019",
 "LUPIN": "NSE_EQ|INE326A01037",
 "GODREJCP": "NSE_EQ|INE102D01028",
 "MARICO": "NSE_EQ|INE196A01026",
 "TATACONSUM": "NSE_EQ|INE192A01025",
 "RVNL": "NSE_EQ|INE415G01027",
 "KPITTECH": "NSE_EQ|INE04I401011",
 "JUBLPHARMA": "NSE_EQ|INE700A01033",
 "ECLERX": "NSE_EQ|INE738I01010",
 "DOMS": "NSE_EQ|INE321T01012",
 "INOXWIND": "NSE_EQ|INE066P01011",
 "GRAVITA": "NSE_EQ|INE024L01027",
 "CONCORDBIO": "NSE_EQ|INE338H01029",
 "LTFOODS": "NSE_EQ|INE818H01020",
 "KEC": "NSE_EQ|INE389H01022",
 "SCI": "NSE_EQ|INE109A01011",
 "TRIDENT": "NSE_EQ|INE064C01022",
 "TEGA": "NSE_EQ|INE011K01018",
 "ACE": "NSE_EQ|INE731H01025",
 "OLECTRA": "NSE_EQ|INE260D01016",
 "BLUEDART": "NSE_EQ|INE233B01017",
 "JUBLINGREA": "NSE_EQ|INE0BY001018",
 "NUVOCO": "NSE_EQ|INE118D01016",
 "TITAGARH": "NSE_EQ|INE615H01020",
 "MGL": "NSE_EQ|INE002S01010",
 "JWL": "NSE_EQ|INE209L01016",
 "HEG": "NSE_EQ|INE545A01024",
 "WHIRLPOOL": "NSE_EQ|INE716A01013",
 "RAILTEL": "NSE_EQ|INE0DD101019",
 "CYIENT": "NSE_EQ|INE136B01020",
 "NCC": "NSE_EQ|INE868B01028",
 "BATAINDIA": "NSE_EQ|INE176A01028",
 "RHIM": "NSE_EQ|INE743M01012",
 "BSOFT": "NSE_EQ|INE836A01035",
 "SONATSOFTW": "NSE_EQ|INE269A01021",
 "SPLPETRO": "NSE_EQ|INE663A01033",
 "MAXHEALTH": "NSE_EQ|INE027H01010",
 "JINDALSTEL": "NSE_EQ|INE749A01030",
 "INDUSTOWER": "NSE_EQ|INE121J01017",
 "DRREDDY": "NSE_EQ|INE089A01031",
 "HEROMOTOCO": "NSE_EQ|INE158A01026",
 "AUROPHARMA": "NSE_EQ|INE406A01037",
 "SRF": "NSE_EQ|INE647A01010",
 "DIXON": "NSE_EQ|INE935N01020",
 "PERSISTENT": "NSE_EQ|INE262H01021",
 "ATGL": "NSE_EQ|INE399L01023",
 "SWIGGY": "NSE_EQ|INE00H001014",
 "HAVELLS": "NSE_EQ|INE176B01034",
 "SUZLON": "NSE_EQ|INE040H01021",
 "FORTIS": "NSE_EQ|INE061F01013",
 "TORNTPOWER": "NSE_EQ|INE813H01021",
 "SAIL": "NSE_EQ|INE114A01011",
 "ALKEM": "NSE_EQ|INE540L01014",
 "UNOMINDA": "NSE_EQ|INE405E01023",
 "COFORGE": "NSE_EQ|INE591G01025",
 "NATIONALUM": "NSE_EQ|INE139A01034",
 "GLENMARK": "NSE_EQ|INE935A01035",
 "SCHAEFFLER": "NSE_EQ|INE513A01022",
 "COROMANDEL": "NSE_EQ|INE169A01031",
 "LINDEINDIA": "NSE_EQ|INE473A01011",
 "JSL": "NSE_EQ|INE220G01021",
 "BERGEPAINT": "NSE_EQ|INE463A01038",
 "TIINDIA": "NSE_EQ|INE974X01010",
 "THERMAX": "NSE_EQ|INE152A01029",
 "MRF": "NSE_EQ|INE883A01011",
 "APARINDS": "NSE_EQ|INE372A01015",
 "COLPAL": "NSE_EQ|INE259A01022",
 "APLAPOLLO": "NSE_EQ|INE702C01027",
 "KEI": "NSE_EQ|INE878B01027",
 "HINDCOPPER": "NSE_EQ|INE531E01026",
 "IPCALAB": "NSE_EQ|INE571A01038",
 "PATANJALI": "NSE_EQ|INE619A01035",
 "MPHASIS": "NSE_EQ|INE356A01018",
 "PAGEIND": "NSE_EQ|INE761H01022",
 "BALKRISIND": "NSE_EQ|INE787D01026",
 "FLUOROCHEM": "NSE_EQ|INE09N301011",
 "VOLTAS": "NSE_EQ|INE226A01021",
 "WELCORP": "NSE_EQ|INE191B01025",
 "SUPREMEIND": "NSE_EQ|INE195A01028",
 "ASTERDM": "NSE_EQ|INE914M01019",
 "PETRONET": "NSE_EQ|INE347G01014",
 "AJANTPHARM": "NSE_EQ|INE031B01049",
 "3MINDIA": "NSE_EQ|INE470A01017",
 "ENDURANCE": "NSE_EQ|INE913H01037",
 "EXIDEIND": "NSE_EQ|INE302A01020",
 "MEDANTA": "NSE_EQ|INE474Q01031",
 "ASTRAL": "NSE_EQ|INE006I01046",
 "LTTS": "NSE_EQ|INE010V01017",
 "EMCURE": "NSE_EQ|INE168P01015",
 "BLUESTARCO": "NSE_EQ|INE472A01039",
 "DALBHARAT": "NSE_EQ|INE00R701025",
 "CRISIL": "NSE_EQ|INE007A01025",
 "WOCKPHARMA": "NSE_EQ|INE049B01025",
 "TATATECH": "NSE_EQ|INE142M01025",
 "SYRMA": "NSE_EQ|INE0DYJ01015",
 "APOLLOTYRE": "NSE_EQ|INE438A01022",
 "ITI": "NSE_EQ|INE248A01017",
 "AMBER": "NSE_EQ|INE371P01015",
 "SHYAMMETL": "NSE_EQ|INE810G01011",
 "NBCC": "NSE_EQ|INE095N01031",
 "SAILIFE": "NSE_EQ|INE570L01029",
 "MSUMI": "NSE_EQ|INE0FS801015",
 "GILLETTE": "NSE_EQ|INE322A01010",
 "RRKABEL": "NSE_EQ|INE777K01022",
 "NEULANDLAB": "NSE_EQ|INE794A01010",
 "NETWEB": "NSE_EQ|INE0NT901020",
 "TIMKEN": "NSE_EQ|INE325A01013",
 "FORCEMOT": "NSE_EQ|INE451A01017",
 "DEEPAKNTR": "NSE_EQ|INE288B01029",
 "GRANULES": "NSE_EQ|INE101D01020",
 "REDINGTON": "NSE_EQ|INE891D01026",
 "IGL": "NSE_EQ|INE203G01027",
 "ANANTRAJ": "NSE_EQ|INE242C01024",
 "CARBORUNIV": "NSE_EQ|INE120A01034",
 "SAGILITY": "NSE_EQ|INE0W2G01015",
 "KAJARIACER": "NSE_EQ|INE217B01036",
 "ZYDUSWELL": "NSE_EQ|INE768C01028",
 "BAYERCROP": "NSE_EQ|INE462A01022",
 "VTL": "NSE_EQ|INE825A01020",
 "FSL": "NSE_EQ|INE684F01012",
 "EMAMILTD": "NSE_EQ|INE548C01032",
 "ATUL": "NSE_EQ|INE100A01010",
 "TATACHEM": "NSE_EQ|INE092A01019",
 "ELGIEQUIP": "NSE_EQ|INE285A01027",
 "CASTROLIND": "NSE_EQ|INE172A01027",
 "CHAMBLFERT": "NSE_EQ|INE085A01013",
 "JYOTICNC": "NSE_EQ|INE980O01024",
 "GABRIEL": "NSE_EQ|INE524A01029",
 "JINDALSAW": "NSE_EQ|INE324A01032",
 "CIEINDIA": "NSE_EQ|INE536H01010",
 "CHENNPETRO": "NSE_EQ|INE178A01016",
 "GPIL": "NSE_EQ|INE177H01039",
 "NAVA": "NSE_EQ|INE725A01030",
 "SYNGENE": "NSE_EQ|INE398R01022",
 "CROMPTON": "NSE_EQ|INE299U01018",
 "PGEL": "NSE_EQ|INE457L01029",
 "TBOTEK": "NSE_EQ|INE673O01025",
 "ARE&M": "NSE_EQ|INE885A01032",
 "SOBHA": "NSE_EQ|INE671H01015",
 "FINCABLES": "NSE_EQ|INE235A01022",
 "BIKAJI": "NSE_EQ|INE00E101023",
 "GALLANTT": "NSE_EQ|INE297H01019",
 "WELSPUNLIV": "NSE_EQ|INE192B01031",
 "CEATLTD": "NSE_EQ|INE482A01020",
 "USHAMART": "NSE_EQ|INE228A01035",
 "ELECON": "NSE_EQ|INE205B01031",
 "AFCONS": "NSE_EQ|INE101I01011",
 "BLUEJET": "NSE_EQ|INE0KBH01020",
 "BBTC": "NSE_EQ|INE050A01025",
 "TARIL": "NSE_EQ|INE763I01026",
 "FIRSTCRY": "NSE_EQ|INE02RE01045",
 "VMM": "NSE_EQ|INE01EA01019"
}